<?xml version="1.0" encoding="UTF-8"?>
<!DOCTYPE struts PUBLIC "-//Apache Software Foundation//DTD Struts  
Configuration 2.1//EN" "http://struts.apache.org/dtds/struts-2.1.dtd">

<struts>
	<package name="default" extends="struts-default">
		<action name="greet" class="com.tedaneblake.GreetingAction" method="execute">
			<result name="success">/results.jsp</result>
			<result name="fail">/fail.jsp</result>
		</action>
		<action name="new_user" class="com.tedaneblake.ActorAction" method="execute">
			<result name="admin">/admin.jsp</result>
			<result name="user">/user.jsp</result>
		</action>
	</package>
</struts>